civipy/__init__.py
civipy/activity.py
civipy/address.py
civipy/contact.py
civipy/contribution.py
civipy/event.py
civipy/exceptions.py
civipy/financial.py
civipy/grant.py
civipy/mailing.py
civipy/membership.py
civipy/note.py
civipy/option_group.py
civipy/order.py
civipy/user.py
civipy/base/__init__.py
civipy/base/base.py
civipy/base/config.py
civipy/interface/__init__.py
civipy/interface/base.py
civipy/interface/query.py
civipy/interface/v3.py
civipy/interface/v4.py
civipy-0.0.7.dist-info/licenses/LICENSE
civipy-0.0.7.dist-info/METADATA
civipy-0.0.7.dist-info/WHEEL
civipy-0.0.7.dist-info/top_level.txt
civipy-0.0.7.dist-info/RECORD
