Metadata-Version: 2.4
Name: civipy
Version: 0.0.7
Summary: CiviCRM v3/v4 REST API Python wrapper
Author-email: Joe Carey <joecarey001@gmail.com>, Ana Nelson <ana@ananelson.com>
License: GPLv3
Project-URL: Homepage, https://git.accountingdatasolutions.com/indepndnt/civipy
Classifier: Development Status :: 2 - Pre-Alpha
Classifier: Programming Language :: Python :: 3.9
Classifier: Programming Language :: Python :: 3.10
Classifier: Programming Language :: Python :: 3.11
Classifier: Programming Language :: Python :: 3.12
Classifier: Programming Language :: Python :: 3.13
Classifier: License :: OSI Approved :: GNU General Public License v3 (GPLv3)
Classifier: Operating System :: OS Independent
Requires-Python: >=3.9
License-File: LICENSE
Requires-Dist: urllib3
Provides-Extra: pyproject
Requires-Dist: tomli>=1.1.0; python_version < "3.11" and extra == "pyproject"
Provides-Extra: dev
Requires-Dist: black; extra == "dev"
Requires-Dist: coverage[toml]; extra == "dev"
Requires-Dist: pytest; extra == "dev"
Requires-Dist: pytest-cov; extra == "dev"
Requires-Dist: ruff; extra == "dev"
Requires-Dist: build; extra == "dev"
Requires-Dist: twine; extra == "dev"
Dynamic: license-file
